[
  {
    "address": "100 I10 WESTBOUND MM100 HW",
    "city": "LAFAYETTE",
    "time": "06/17/2020 - 12:16 AM",
    "due_to": "Vehicle Accident",
    "latitude": 30.26255,
    "longitude": -92.00867
  },
  {
    "address": "1400 N BERTRAND DR",
    "city": "LAFAYETTE",
    "time": "06/16/2020 - 11:14 PM",
    "due_to": "Commercial Fire",
    "latitude": 30.22402,
    "longitude": -92.0514
  },
  {
    "address": "100 WALKER RD",
    "city": "LAFAYETTE",
    "time": "06/16/2020 - 10:47 PM",
    "due_to": "Vehicle Accident w/ Injuries",
    "latitude": 30.23584,
    "longitude": -92.03549
  }
]