[
  {
    "address": "121 LEGEND CREEK DR",
    "city": "LAFAYETTE",
    "time": "08/27/2020 - 08:10 AM",
    "due_to": "Road Hazard",
    "latitude": 30.10781,
    "longitude": -92.05562
  },
  {
    "address": "104 ALVA RD",
    "city": "LAFAYETTE",
    "time": "08/27/2020 - 08:09 AM",
    "due_to": "Road Hazard",
    "latitude": 30.09349,
    "longitude": -91.95737
  },
  {
    "address": "2414 BONIN RD",
    "city": "YOUNGSVILLE",
    "time": "08/27/2020 - 08:07 AM",
    "due_to": "Road Hazard",
    "latitude": 30.11357,
    "longitude": -92.00702
  },
  {
    "address": "W WILLOW ST & AMBASSADOR CAFFERY PW",
    "city": "LAFAYETTE",
    "time": "08/27/2020 - 07:56 AM",
    "due_to": "Vehicle Accident",
    "latitude": 30.24324,
    "longitude": -92.06626
  },
  {
    "address": "W CONGRESS ST & ALYENE DR",
    "city": "LAFAYETTE",
    "time": "08/27/2020 - 07:50 AM",
    "due_to": "Vehicle Accident",
    "latitude": 30.19777,
    "longitude": -92.07116
  },
  {
    "address": "103 BEGNAUD DR",
    "city": "LAFAYETTE",
    "time": "08/27/2020 - 07:47 AM",
    "due_to": "Fire Investigation",
    "latitude": 30.24536,
    "longitude": -91.99588
  },
  {
    "address": "F ST & THIRD ST",
    "city": "DUSON",
    "time": "08/27/2020 - 07:11 AM",
    "due_to": "Road Hazard",
    "latitude": 30.23746,
    "longitude": -92.17887
  },
  {
    "address": "HORIZON LN & DUGAS RD",
    "city": "LAFAYETTE",
    "time": "08/27/2020 - 07:07 AM",
    "due_to": "Road Hazard",
    "latitude": 30.28326,
    "longitude": -92.08884
  },
  {
    "address": "AMBASSADOR CAFFERY PW & DULLES DR",
    "city": "LAFAYETTE",
    "time": "08/27/2020 - 06:20 AM",
    "due_to": "Traffic Control",
    "latitude": 30.21054,
    "longitude": -92.07569
  },
  {
    "address": "146 E KALISTE SALOOM RD",
    "city": "LAFAYETTE",
    "time": "08/27/2020 - 05:49 AM",
    "due_to": "Road Hazard",
    "latitude": 30.1914031,
    "longitude": -92.0117821
  },
  {
    "address": "100 CREST CL",
    "city": "YOUNGSVILLE",
    "time": "08/27/2020 - 04:59 AM",
    "due_to": "Road Hazard",
    "latitude": 30.11234,
    "longitude": -92.0071
  },
  {
    "address": "110 CHURCHILL DR",
    "city": "LAFAYETTE",
    "time": "08/27/2020 - 03:44 AM",
    "due_to": "Residential Fire",
    "latitude": 30.19584,
    "longitude": -92.05858
  },
  {
    "address": "N UNIVERSITY AV & RAILROAD UNDERPASS",
    "city": "LAFAYETTE",
    "time": "08/27/2020 - 03:04 AM",
    "due_to": "Road Hazard",
    "latitude": 30.24052,
    "longitude": -92.03242
  },
  {
    "address": "LOUISIANA AV & I10 HW",
    "city": "LAFAYETTE",
    "time": "08/27/2020 - 01:21 AM",
    "due_to": "Traffic Signal Malfunction",
    "latitude": 30.27944,
    "longitude": -91.99217
  }
]