[
  {
    "address": "551 BENOIT FALGOUT DR",
    "city": "LAFAYETTE",
    "time": "05/30/2019 - 2:47 PM",
    "due_to": "Vehicle Accident w/ Injuries",
    "latitude": 30.2556731,
    "longitude": -92.0238428
  },
  {
    "address": "1251 BIRDSONG RD",
    "city": "LAFAYETTE",
    "time": "05/30/2019 - 2:15 PM",
    "due_to": "Vehicle Accident w/ Injuries",
    "latitude": 30.277387,
    "longitude": -92.0486267
  },
  {
    "address": "2404 GENDARME RD",
    "city": "LAFAYETTE",
    "time": "05/30/2019 - 1:18 PM",
    "due_to": "Residential Fire",
    "latitude": 30.32903,
    "longitude": -92.08545
  },
  {
    "address": "I49 NORTHBOUND MM3 HW & E GLORIA SWITCH RD",
    "city": "CARENCRO",
    "time": "05/30/2019 - 09:28 AM",
    "due_to": "Traffic Control",
    "latitude": 30.29523,
    "longitude": -92.01609
  }
]