[
  {
    "address": "KALISTE SALOOM RD & STEINER RD",
    "city": "LAFAYETTE",
    "time": "08/20/2020 - 4:18 PM",
    "due_to": "Vehicle Accident",
    "latitude": 30.17082,
    "longitude": -92.03184
  },
  {
    "address": "W PINHOOK RD & SOUTHPARK RD",
    "city": "LAFAYETTE",
    "time": "08/20/2020 - 4:13 PM",
    "due_to": "Vehicle Accident",
    "latitude": 30.16071,
    "longitude": -91.99107
  },
  {
    "address": "ST CHARLES ST & LOUISIANA AV",
    "city": "LAFAYETTE",
    "time": "08/20/2020 - 3:55 PM",
    "due_to": "Vehicle Accident w/ Injuries",
    "latitude": 30.22449,
    "longitude": -92.00205
  },
  {
    "address": "W CONGRESS ST & BERTRAND DR",
    "city": "LAFAYETTE",
    "time": "08/20/2020 - 3:45 PM",
    "due_to": "Vehicle Accident",
    "latitude": 30.21493,
    "longitude": -92.04696
  },
  {
    "address": "OLD CAMP RD & MEADOW FARM RD",
    "city": "LAFAYETTE",
    "time": "08/20/2020 - 3:23 PM",
    "due_to": "Vehicle Accident",
    "latitude": 30.15755,
    "longitude": -92.0433
  },
  {
    "address": "JOHNSTON ST & ST JULIEN AV",
    "city": "LAFAYETTE",
    "time": "08/20/2020 - 3:14 PM",
    "due_to": "Vehicle Accident",
    "latitude": 30.21151,
    "longitude": -92.02691
  },
  {
    "address": "300 JESSICA ST",
    "city": "LAFAYETTE",
    "time": "08/20/2020 - 2:06 PM",
    "due_to": "Vehicle Accident w/ Injuries",
    "latitude": 30.2554159,
    "longitude": -92.0229627
  }
]