[
  {
    "address": "SW EVANGELINE TW & JOHNSTON ST",
    "city": "LAFAYETTE",
    "time": "05/19/2019 - 09:16 AM",
    "due_to": "Traffic Signal Malfunction",
    "latitude": 30.22457,
    "longitude": -92.01033
  },
  {
    "address": "55 BNSF RAILROAD CG",
    "city": "DUSON",
    "time": "05/19/2019 - 09:01 AM",
    "due_to": "Traffic Signal Malfunction",
    "latitude": 30.1725,
    "longitude": -92.1407
  },
  {
    "address": "PANDORA ST & PLAZA VILLAGE DR",
    "city": "LAFAYETTE",
    "time": "05/19/2019 - 08:57 AM",
    "due_to": "Vehicle Accident w/ Injuries",
    "latitude": 30.20283,
    "longitude": -92.06703
  },
  {
    "address": "110 THEO ST",
    "city": "LAFAYETTE",
    "time": "05/19/2019 - 08:14 AM",
    "due_to": "Vehicle Accident",
    "latitude": 30.19547,
    "longitude": -92.00218
  },
  {
    "address": "BEAU BASSIN RD & FARMVIEW DR",
    "city": "LAFAYETTE",
    "time": "05/19/2019 - 08:02 AM",
    "due_to": "Road Hazard",
    "latitude": 30.31388,
    "longitude": -91.99424
  },
  {
    "address": "5000 MOSS ST",
    "city": "LAFAYETTE",
    "time": "05/19/2019 - 07:38 AM",
    "due_to": "Road Hazard",
    "latitude": 30.300904,
    "longitude": -92.0094865
  },
  {
    "address": "E BROUSSARD RD & ROBLEY DR",
    "city": "LAFAYETTE",
    "time": "05/19/2019 - 07:37 AM",
    "due_to": "Road Hazard",
    "latitude": 30.14301,
    "longitude": -92.0795
  },
  {
    "address": "LEISURE LN & MARIE ANTOINETTE ST",
    "city": "LAFAYETTE",
    "time": "05/19/2019 - 07:27 AM",
    "due_to": "Hazardous Material",
    "latitude": 30.21268,
    "longitude": -92.06418
  }
]