[
  {
    "address": "SETTLERS TRACE BL & RUE POEYFARRE",
    "city": "LAFAYETTE",
    "time": "06/24/2019 - 10:27 AM",
    "due_to": "Vehicle Accident",
    "latitude": 30.17043,
    "longitude": -92.03703
  },
  {
    "address": "3225 LOUISIANA AV",
    "city": "LAFAYETTE",
    "time": "06/24/2019 - 10:21 AM",
    "due_to": "Vehicle Accident",
    "latitude": 30.2657,
    "longitude": -91.99574
  },
  {
    "address": "1020 NE EVANGELINE TW",
    "city": "LAFAYETTE",
    "time": "06/24/2019 - 10:14 AM",
    "due_to": "Vehicle Accident",
    "latitude": 30.23689,
    "longitude": -92.01261
  },
  {
    "address": "3201 KALISTE SALOOM RD",
    "city": "LAFAYETTE",
    "time": "06/24/2019 - 09:48 AM",
    "due_to": "Vehicle Accident",
    "latitude": 30.1474482,
    "longitude": -92.0566429
  }
]