[
  {
    "address": "ERASTE LANDRY RD & AMBASSADOR CAFFERY PW",
    "city": "LAFAYETTE",
    "time": "07/11/2019 - 5:12 PM",
    "due_to": "Traffic Signal Malfunction",
    "latitude": 30.21912,
    "longitude": -92.07587
  },
  {
    "address": "SW EVANGELINE TW & E UNIVERSITY AV",
    "city": "LAFAYETTE",
    "time": "07/11/2019 - 5:11 PM",
    "due_to": "Stalled Vehicle",
    "latitude": 30.20908,
    "longitude": -92.00007
  },
  {
    "address": "VEROT SCHOOL RD & GRANDVIEW TERRACE DR",
    "city": "LAFAYETTE",
    "time": "07/11/2019 - 5:13 PM",
    "due_to": "Fire Investigation",
    "latitude": 30.11468,
    "longitude": -92.03244
  },
  {
    "address": "SE EVANGELINE TW & E VEROT SCHOOL RD",
    "city": "LAFAYETTE",
    "time": "07/11/2019 - 5:06 PM",
    "due_to": "Traffic Signal Malfunction",
    "latitude": 30.18291,
    "longitude": -91.98959
  },
  {
    "address": "2863 AMBASSADOR CAFFERY PW",
    "city": "LAFAYETTE",
    "time": "07/11/2019 - 4:28 PM",
    "due_to": "Vehicle Accident",
    "latitude": 30.19816,
    "longitude": -92.07417
  },
  {
    "address": "AMBASSADOR CAFFERY PW & RIDGE RD",
    "city": "LAFAYETTE",
    "time": "07/11/2019 - 3:47 PM",
    "due_to": "Vehicle Accident",
    "latitude": 30.21504,
    "longitude": -92.07579
  },
  {
    "address": "325 E MAIN ST",
    "city": "LAFAYETTE",
    "time": "07/11/2019 - 2:41 PM",
    "due_to": "Vehicle Accident",
    "latitude": 30.22258,
    "longitude": -92.01631
  }
]