[
  {
    "address": "BENDEL RD & MARGUERITE BL",
    "city": "LAFAYETTE",
    "time": "02/01/2020 - 9:35 PM",
    "due_to": "Vehicle Accident",
    "latitude": 30.20083,
    "longitude": -92.0186
  },
  {
    "address": "251 CHEYENNE CL",
    "city": "SCOTT",
    "time": "02/01/2020 - 9:17 PM",
    "due_to": "Fire Investigation",
    "latitude": 30.2257777,
    "longitude": -92.0909649
  },
  {
    "address": "W GLORIA SWITCH RD & LUMINA DR",
    "city": "CARENCRO",
    "time": "02/01/2020 - 7:42 PM",
    "due_to": "Vehicle Accident",
    "latitude": 30.296,
    "longitude": -92.03198
  }
]