[
  {
    "address": "1441 SE EVANGELINE TW",
    "city": "LAFAYETTE",
    "time": "07/10/2020 - 8:23 PM",
    "due_to": "Fire Investigation",
    "latitude": 30.2168564,
    "longitude": -92.003308
  },
  {
    "address": "PACKARD ST & MOSS ST",
    "city": "LAFAYETTE",
    "time": "07/10/2020 - 8:05 PM",
    "due_to": "Vehicle Accident w/ Injuries",
    "latitude": 30.25257,
    "longitude": -92.00531
  },
  {
    "address": "1812 W PINHOOK RD",
    "city": "LAFAYETTE",
    "time": "07/10/2020 - 8:04 PM",
    "due_to": "Stalled Vehicle",
    "latitude": 30.19084,
    "longitude": -92.01621
  }
]