[
  {
    "address": "WALKER RD & SAUCIER PW",
    "city": "LAFAYETTE",
    "time": "05/16/2020 - 10:12 AM",
    "due_to": "Fire Investigation",
    "latitude": 30.23555,
    "longitude": -92.04201
  },
  {
    "address": "1130 DUHON RD",
    "city": "LAFAYETTE",
    "time": "05/16/2020 - 10:07 AM",
    "due_to": "Residential Fire",
    "latitude": 30.17093,
    "longitude": -92.116
  },
  {
    "address": "200 HECTOR CONNOLY RD",
    "city": "CARENCRO",
    "time": "05/16/2020 - 09:59 AM",
    "due_to": "Fire Investigation",
    "latitude": 30.32242,
    "longitude": -92.03036
  },
  {
    "address": "510 LA FLAMME RD",
    "city": "LAFAYETTE",
    "time": "05/16/2020 - 09:08 AM",
    "due_to": "Traffic Control",
    "latitude": 30.1472,
    "longitude": -91.93506
  }
]