[
  {
    "address": "105 SAVIGNON CL",
    "city": "BROUSSARD",
    "time": "06/28/2020 - 2:27 PM",
    "due_to": "Fire Investigation",
    "latitude": 30.16425,
    "longitude": -91.95971
  },
  {
    "address": "200 PETROLEUM RD (SE)",
    "city": "LAFAYETTE",
    "time": "06/28/2020 - 2:25 PM",
    "due_to": "Incoming Call",
    "latitude": 30.1652665,
    "longitude": -91.9840227
  },
  {
    "address": "300 RUE DE LA VACHE",
    "city": "LAFAYETTE",
    "time": "06/28/2020 - 2:20 PM",
    "due_to": "Stalled Vehicle",
    "latitude": 30.2724471,
    "longitude": -92.0964733
  },
  {
    "address": "E PINHOOK RD & SW EVANGELINE TW",
    "city": "LAFAYETTE",
    "time": "06/28/2020 - 2:14 PM",
    "due_to": "Stalled Vehicle",
    "latitude": 30.21749,
    "longitude": -92.00495
  },
  {
    "address": "2426 W CONGRESS ST",
    "city": "LAFAYETTE",
    "time": "06/28/2020 - 1:52 PM",
    "due_to": "Vehicle Accident",
    "latitude": 30.21379,
    "longitude": -92.04917
  },
  {
    "address": "3910 AMBASSADOR CAFFERY PW",
    "city": "LAFAYETTE",
    "time": "06/28/2020 - 1:49 PM",
    "due_to": "Vehicle Accident",
    "latitude": 30.16691,
    "longitude": -92.06199
  },
  {
    "address": "JOHNSTON ST & ARNOULD BL",
    "city": "LAFAYETTE",
    "time": "06/28/2020 - 1:42 PM",
    "due_to": "Vehicle Accident",
    "latitude": 30.20186,
    "longitude": -92.05312
  },
  {
    "address": "4576 MOSS ST",
    "city": "LAFAYETTE",
    "time": "06/28/2020 - 1:39 PM",
    "due_to": "Vehicle Accident",
    "latitude": 30.2945119,
    "longitude": -92.0071451
  },
  {
    "address": "3521 W PINHOOK RD",
    "city": "LAFAYETTE",
    "time": "06/28/2020 - 1:27 PM",
    "due_to": "Vehicle Accident w/ Injuries",
    "latitude": 30.16169,
    "longitude": -91.99173
  },
  {
    "address": "1102 ALFRED ST",
    "city": "SCOTT",
    "time": "06/28/2020 - 1:19 PM",
    "due_to": "Vehicle Accident",
    "latitude": 30.23604,
    "longitude": -92.09406
  },
  {
    "address": "W PINHOOK RD & SOUTHPARK RD",
    "city": "LAFAYETTE",
    "time": "06/28/2020 - 1:17 PM",
    "due_to": "Vehicle Accident w/ Injuries",
    "latitude": 30.16071,
    "longitude": -91.99107
  }
]