[
  {
    "address": "W PINHOOK RD & SOUTHPARK RD",
    "city": "LAFAYETTE",
    "time": "05/30/2019 - 07:55 AM",
    "due_to": "Vehicle Accident",
    "latitude": 30.16071,
    "longitude": -91.99107
  },
  {
    "address": "1214 COOLIDGE ST",
    "city": "LAFAYETTE",
    "time": "05/30/2019 - 07:50 AM",
    "due_to": "Hazardous Material",
    "latitude": 30.2025101,
    "longitude": -92.0186946
  },
  {
    "address": "E PONT DES MOUTON RD & HIGH MEADOWS BL",
    "city": "LAFAYETTE",
    "time": "05/30/2019 - 07:41 AM",
    "due_to": "Vehicle Accident",
    "latitude": 30.27337,
    "longitude": -92.01605
  },
  {
    "address": "1345 W WILLOW ST",
    "city": "LAFAYETTE",
    "time": "05/30/2019 - 07:35 AM",
    "due_to": "Fire Alarm-Commercial",
    "latitude": 30.24372,
    "longitude": -92.03862
  },
  {
    "address": "1701 N UNIVERSITY AV",
    "city": "LAFAYETTE",
    "time": "05/30/2019 - 06:43 AM",
    "due_to": "Hazardous Material",
    "latitude": 30.25216,
    "longitude": -92.03842
  }
]