[
  {
    "address": "5611 JOHNSTON ST",
    "city": "LAFAYETTE",
    "time": "03/21/2019 - 7:54 PM",
    "due_to": "Vehicle Accident",
    "latitude": 30.17723,
    "longitude": -92.07457
  },
  {
    "address": "103 DELHOMME AV",
    "city": "SCOTT",
    "time": "03/21/2019 - 6:22 PM",
    "due_to": "Vehicle Accident",
    "latitude": 30.23545,
    "longitude": -92.09144
  },
  {
    "address": "4715 NW EVANGELINE TW",
    "city": "LAFAYETTE",
    "time": "03/21/2019 - 6:18 PM",
    "due_to": "Vehicle Accident w/ Injuries",
    "latitude": 30.36041,
    "longitude": -92.04821
  }
]