[
  {
    "address": "204 JERRY ST",
    "city": "LAFAYETTE",
    "time": "07/10/2019 - 07:44 AM",
    "due_to": "Fire Alarm-Residential",
    "latitude": 30.15295,
    "longitude": -92.08528
  },
  {
    "address": "US 90 EAST HW & N GIROUARD RD",
    "city": "BROUSSARD",
    "time": "07/10/2019 - 07:31 AM",
    "due_to": "Stalled Vehicle",
    "latitude": 30.14854,
    "longitude": -91.9488
  },
  {
    "address": "102 I10 WB EXIT RAMP HW",
    "city": "LAFAYETTE",
    "time": "07/10/2019 - 07:01 AM",
    "due_to": "Vehicle Accident",
    "latitude": 30.26255,
    "longitude": -92.00867
  }
]