[
  {
    "address": "120 E GLORIA SWITCH RD",
    "city": "LAFAYETTE",
    "time": "06/18/2019 - 7:47 PM",
    "due_to": "Vehicle Accident",
    "latitude": 30.29346,
    "longitude": -92.02171
  },
  {
    "address": "3420 NE EVANGELINE TW",
    "city": "CARENCRO",
    "time": "06/18/2019 - 7:46 PM",
    "due_to": "Road Hazard",
    "latitude": 30.30293,
    "longitude": -92.02633
  },
  {
    "address": "JOHNSTON ST & CAMELLIA BL",
    "city": "LAFAYETTE",
    "time": "06/18/2019 - 7:43 PM",
    "due_to": "Vehicle Accident",
    "latitude": 30.19364,
    "longitude": -92.0587
  }
]