[
  {
    "address": "MARIE ANTOINETTE ST & W CONGRESS ST",
    "city": "LAFAYETTE",
    "time": "07/16/2019 - 8:10 PM",
    "due_to": "Vehicle Accident",
    "latitude": 30.20609,
    "longitude": -92.05834
  },
  {
    "address": "3806 AMBASSADOR CAFFERY PW",
    "city": "LAFAYETTE",
    "time": "07/16/2019 - 7:53 PM",
    "due_to": "Traffic Control",
    "latitude": 30.17072,
    "longitude": -92.06613
  },
  {
    "address": "1400 N BERTRAND DR",
    "city": "LAFAYETTE",
    "time": "07/16/2019 - 7:50 PM",
    "due_to": "Fire Alarm-Commercial",
    "latitude": 30.22402,
    "longitude": -92.0514
  },
  {
    "address": "1521 W PINHOOK RD",
    "city": "LAFAYETTE",
    "time": "07/16/2019 - 7:25 PM",
    "due_to": "Vehicle Accident",
    "latitude": 30.19637,
    "longitude": -92.01545
  }
]