[
  {
    "address": "1825 W PINHOOK RD",
    "city": "LAFAYETTE",
    "time": "04/28/2019 - 12:05 PM",
    "due_to": "Vehicle Accident w/ Injuries",
    "latitude": 30.1898,
    "longitude": -92.01499
  },
  {
    "address": "615 LA 93 HW",
    "city": "SCOTT",
    "time": "04/28/2019 - 12:00 PM",
    "due_to": "Vehicle Accident",
    "latitude": 30.2609,
    "longitude": -92.1087
  },
  {
    "address": "302 WEST MAIN",
    "city": "Lafayette",
    "time": "04/28/2019 - 11:56 AM",
    "due_to": "Traffic Control",
    "latitude": 30.2230449,
    "longitude": -92.0209788
  },
  {
    "address": "3011 NW EVANGELINE TW",
    "city": "LAFAYETTE",
    "time": "04/28/2019 - 11:40 AM",
    "due_to": "Vehicle Accident",
    "latitude": 30.2843,
    "longitude": -92.02272
  },
  {
    "address": "AMBASSADOR CAFFERY PW & FREM BOUSTANY DR",
    "city": "LAFAYETTE",
    "time": "04/28/2019 - 11:28 AM",
    "due_to": "Vehicle Accident",
    "latitude": 30.15011,
    "longitude": -92.0406
  }
]