[
  {
    "address": "US 90 EAST HW & ST NAZAIRE RD",
    "city": "BROUSSARD",
    "time": "08/14/2019 - 4:15 PM",
    "due_to": "Vehicle Accident",
    "latitude": 30.1406051,
    "longitude": -91.9448999
  },
  {
    "address": "CHEMIN METAIRIE PW & GUILLIOT RD",
    "city": "YOUNGSVILLE",
    "time": "08/14/2019 - 3:47 PM",
    "due_to": "Stalled Vehicle",
    "latitude": 30.09013,
    "longitude": -92.00377
  },
  {
    "address": "907 S STERLING ST",
    "city": "LAFAYETTE",
    "time": "08/14/2019 - 3:33 PM",
    "due_to": "Vehicle Accident",
    "latitude": 30.22435,
    "longitude": -92.00283
  },
  {
    "address": "251 N MICHAUD ST",
    "city": "CARENCRO",
    "time": "08/14/2019 - 3:29 PM",
    "due_to": "Stalled Vehicle",
    "latitude": 30.3236278,
    "longitude": -92.0447155
  },
  {
    "address": "200 SONNIER RD",
    "city": "LAFAYETTE",
    "time": "08/14/2019 - 3:14 PM",
    "due_to": "Stalled Vehicle",
    "latitude": 30.31745,
    "longitude": -92.02023
  }
]