[
  {
    "address": "119 TUCKER DR",
    "city": "LAFAYETTE",
    "time": "04/19/2019 - 6:08 PM",
    "due_to": "Vehicle Accident",
    "latitude": 30.17372,
    "longitude": -92.07168
  },
  {
    "address": "3142 AMBASSADOR CAFFERY PW",
    "city": "LAFAYETTE",
    "time": "04/19/2019 - 6:04 PM",
    "due_to": "Vehicle Accident",
    "latitude": 30.1873,
    "longitude": -92.07797
  },
  {
    "address": "231 W WILLOW ST",
    "city": "LAFAYETTE",
    "time": "04/19/2019 - 5:55 PM",
    "due_to": "Vehicle Accident w/ Injuries",
    "latitude": 30.24482,
    "longitude": -92.01663
  },
  {
    "address": "JOHNSTON ST & S WESTMARK BL",
    "city": "LAFAYETTE",
    "time": "04/19/2019 - 3:55 PM",
    "due_to": "Vehicle Accident w/ Injuries",
    "latitude": 30.1824,
    "longitude": -92.07019
  }
]