[
  {
    "address": "AMBASSADOR CAFFERY PW & VEROT SCHOOL RD",
    "city": "LAFAYETTE",
    "time": "06/10/2020 - 10:37 AM",
    "due_to": "Vehicle Accident",
    "latitude": 30.14589,
    "longitude": -92.03252
  },
  {
    "address": "AMBASSADOR CAFFERY PW & LA NEUVILLE RD",
    "city": "LAFAYETTE",
    "time": "06/10/2020 - 10:26 AM",
    "due_to": "Vehicle Accident",
    "latitude": 30.14065,
    "longitude": -92.02448
  },
  {
    "address": "4400 NW EVANGELINE TW",
    "city": "LAFAYETTE",
    "time": "06/10/2020 - 10:23 AM",
    "due_to": "Vehicle Accident w/ Injuries",
    "latitude": 30.34824,
    "longitude": -92.04415
  },
  {
    "address": "2106 NE EVANGELINE TW",
    "city": "LAFAYETTE",
    "time": "06/10/2020 - 10:16 AM",
    "due_to": "Vehicle Accident",
    "latitude": 30.25257,
    "longitude": -92.01327
  },
  {
    "address": "I49 NORTHBOUND HW & I10 OVERPASS MM103 HW",
    "city": "LAFAYETTE",
    "time": "06/10/2020 - 10:02 AM",
    "due_to": "Traffic Control",
    "latitude": 30.26255,
    "longitude": -92.00867
  },
  {
    "address": "202 BRAHMAN DR",
    "city": "YOUNGSVILLE",
    "time": "06/10/2020 - 09:58 AM",
    "due_to": "Commercial Fire",
    "latitude": 30.1241,
    "longitude": -91.99562
  },
  {
    "address": "5593 JOHNSTON ST",
    "city": "LAFAYETTE",
    "time": "06/10/2020 - 09:52 AM",
    "due_to": "Vehicle Accident",
    "latitude": 30.1785953,
    "longitude": -92.0738257
  }
]