[
  {
    "address": "ROME LN & RUE SCHOLASTIQUE",
    "city": "LAFAYETTE",
    "time": "06/05/2019 - 1:35 PM",
    "due_to": "Vehicle Accident",
    "latitude": 30.28774,
    "longitude": -92.10883
  },
  {
    "address": "W PINHOOK RD & E KALISTE SALOOM RD",
    "city": "LAFAYETTE",
    "time": "06/05/2019 - 1:34 PM",
    "due_to": "Vehicle Accident",
    "latitude": 30.1886,
    "longitude": -92.0141
  },
  {
    "address": "MUDD AV & LOUISIANA AV",
    "city": "LAFAYETTE",
    "time": "06/05/2019 - 1:30 PM",
    "due_to": "Vehicle Accident",
    "latitude": 30.23174,
    "longitude": -92.0027
  },
  {
    "address": "3557 AMBASSADOR CAFFERY PW",
    "city": "LAFAYETTE",
    "time": "06/05/2019 - 1:11 PM",
    "due_to": "Vehicle Accident",
    "latitude": 30.17641,
    "longitude": -92.07227
  },
  {
    "address": "KALISTE SALOOM RD & E BROUSSARD RD",
    "city": "LAFAYETTE",
    "time": "06/05/2019 - 12:51 PM",
    "due_to": "Vehicle Accident",
    "latitude": 30.13792,
    "longitude": -92.06754
  },
  {
    "address": "2606 AMBASSADOR CAFFERY PW",
    "city": "LAFAYETTE",
    "time": "06/05/2019 - 12:42 PM",
    "due_to": "Vehicle Accident",
    "latitude": 30.2030673,
    "longitude": -92.0754049
  },
  {
    "address": "JOHNSTON ST & W LEWIS ST",
    "city": "LAFAYETTE",
    "time": "06/05/2019 - 12:19 PM",
    "due_to": "Vehicle Accident w/ Injuries",
    "latitude": 30.21228,
    "longitude": -92.02543
  },
  {
    "address": "3550 AMBASSADOR CAFFERY PW",
    "city": "LAFAYETTE",
    "time": "06/05/2019 - 12:13 PM",
    "due_to": "Vehicle Accident",
    "latitude": 30.17527,
    "longitude": -92.07228
  },
  {
    "address": "KALISTE SALOOM RD & W FARREL RD",
    "city": "LAFAYETTE",
    "time": "06/05/2019 - 12:04 PM",
    "due_to": "Vehicle Accident",
    "latitude": 30.15466,
    "longitude": -92.05015
  }
]