[
  {
    "address": "HECTOR CONNOLY RD & NE EVANGELINE TW",
    "city": "LAFAYETTE",
    "time": "07/12/2019 - 11:46 AM",
    "due_to": "Vehicle Accident",
    "latitude": 30.32261,
    "longitude": -92.0325
  },
  {
    "address": "930 VETERANS DR",
    "city": "CARENCRO",
    "time": "07/12/2019 - 11:43 AM",
    "due_to": "Stalled Vehicle",
    "latitude": 30.32148,
    "longitude": -92.03637
  },
  {
    "address": "1701 N UNIVERSITY AV",
    "city": "LAFAYETTE",
    "time": "07/12/2019 - 11:34 AM",
    "due_to": "Vehicle Accident",
    "latitude": 30.25216,
    "longitude": -92.03842
  },
  {
    "address": "MOSS ST & E PONT DES MOUTON RD",
    "city": "LAFAYETTE",
    "time": "07/12/2019 - 11:31 AM",
    "due_to": "Vehicle Accident",
    "latitude": 30.27304,
    "longitude": -92.00812
  },
  {
    "address": "1800 W UNIVERSITY AV",
    "city": "LAFAYETTE",
    "time": "07/12/2019 - 10:11 AM",
    "due_to": "Vehicle Accident",
    "latitude": 30.22956,
    "longitude": -92.03028
  },
  {
    "address": "NE EVANGELINE TW & E WILLOW ST",
    "city": "LAFAYETTE",
    "time": "07/12/2019 - 10:10 AM",
    "due_to": "Vehicle Accident",
    "latitude": 30.24447,
    "longitude": -92.01187
  }
]