[
  {
    "address": "NW EVANGELINE TW & HOBSON ST",
    "city": "LAFAYETTE",
    "time": "06/24/2019 - 07:54 AM",
    "due_to": "Vehicle Accident",
    "latitude": 30.23394,
    "longitude": -92.01394
  },
  {
    "address": "2631 SE EVANGELINE TW",
    "city": "LAFAYETTE",
    "time": "06/24/2019 - 07:03 AM",
    "due_to": "Vehicle Accident",
    "latitude": 30.18307,
    "longitude": -91.98896
  },
  {
    "address": "1400 S COLLEGE RD",
    "city": "LAFAYETTE",
    "time": "06/24/2019 - 06:21 AM",
    "due_to": "Vehicle Accident w/ Injuries",
    "latitude": 30.2013113,
    "longitude": -92.0193132
  }
]