[
  {
    "address": "3300 LOUISIANA AV",
    "city": "LAFAYETTE",
    "time": "03/21/2019 - 2:55 PM",
    "due_to": "Stalled Vehicle",
    "latitude": 30.2694378,
    "longitude": -91.9921841
  },
  {
    "address": "5725 JOHNSTON ST",
    "city": "LAFAYETTE",
    "time": "03/21/2019 - 2:52 PM",
    "due_to": "Vehicle Accident",
    "latitude": 30.17353,
    "longitude": -92.07732
  },
  {
    "address": "1522 CARMEL DR",
    "city": "LAFAYETTE",
    "time": "03/21/2019 - 2:44 PM",
    "due_to": "Traffic Control",
    "latitude": 30.23215,
    "longitude": -91.98358
  },
  {
    "address": "100 E BROUSSARD RD",
    "city": "LAFAYETTE",
    "time": "03/21/2019 - 2:38 PM",
    "due_to": "Vehicle Accident",
    "latitude": 30.1503691,
    "longitude": -92.0936841
  },
  {
    "address": "302 W MAIN ST",
    "city": "Lafayette",
    "time": "03/21/2019 - 2:20 PM",
    "due_to": "Traffic Control",
    "latitude": 30.2230449,
    "longitude": -92.0209788
  },
  {
    "address": "W PINHOOK RD & EXCHANGE PL",
    "city": "LAFAYETTE",
    "time": "03/21/2019 - 2:01 PM",
    "due_to": "Vehicle Accident",
    "latitude": 30.20232,
    "longitude": -92.0146
  },
  {
    "address": "NW EVANGELINE TW & W WILLOW ST",
    "city": "LAFAYETTE",
    "time": "03/21/2019 - 08:56 AM",
    "due_to": "Vehicle Accident",
    "latitude": 30.24466,
    "longitude": -92.01336
  }
]