[
  {
    "address": "846 HEART D FARM RD",
    "city": "BROUSSARD",
    "time": "05/31/2020 - 11:45 AM",
    "due_to": "Trash Fire",
    "latitude": 30.1307869,
    "longitude": -91.981896
  },
  {
    "address": "5620 JOHNSTON ST",
    "city": "LAFAYETTE",
    "time": "05/31/2020 - 11:40 AM",
    "due_to": "Vehicle Accident",
    "latitude": 30.1779,
    "longitude": -92.07559
  },
  {
    "address": "3142 AMBASSADOR CAFFERY PW",
    "city": "LAFAYETTE",
    "time": "05/31/2020 - 10:36 AM",
    "due_to": "Vehicle Accident",
    "latitude": 30.1873,
    "longitude": -92.07797
  }
]