[
  {
    "address": "SE EVANGELINE TW & LOUISIANA AV",
    "city": "LAFAYETTE",
    "time": "03/17/2019 - 09:06 AM",
    "due_to": "Vehicle Accident",
    "latitude": 30.22488,
    "longitude": -92.00947
  },
  {
    "address": "1220 AMBASSADOR CAFFERY PW",
    "city": "LAFAYETTE",
    "time": "03/17/2019 - 09:04 AM",
    "due_to": "Stalled Vehicle",
    "latitude": 30.22576,
    "longitude": -92.06882
  },
  {
    "address": "231 ST NAZAIRE RD",
    "city": "BROUSSARD",
    "time": "03/17/2019 - 09:01 AM",
    "due_to": "Stalled Vehicle",
    "latitude": 30.1429,
    "longitude": -91.93815
  },
  {
    "address": "2100 SURREY ST",
    "city": "LAFAYETTE",
    "time": "03/17/2019 - 08:09 AM",
    "due_to": "Vehicle Accident",
    "latitude": 30.20896,
    "longitude": -91.9972
  }
]