[
  {
    "address": "105 FLOYD ST",
    "city": "LAFAYETTE",
    "time": "07/09/2020 - 5:37 PM",
    "due_to": "Grass Fire",
    "latitude": 30.2449,
    "longitude": -92.01909
  },
  {
    "address": "AMBASSADOR CAFFERY PW & VEROT SCHOOL RD",
    "city": "LAFAYETTE",
    "time": "07/09/2020 - 5:06 PM",
    "due_to": "Stalled Vehicle",
    "latitude": 30.14589,
    "longitude": -92.03252
  },
  {
    "address": "W CONGRESS ST & BERTRAND DR",
    "city": "LAFAYETTE",
    "time": "07/09/2020 - 4:23 PM",
    "due_to": "Vehicle Accident",
    "latitude": 30.21493,
    "longitude": -92.04696
  }
]