[
  {
    "address": "W UNIVERSITY AV & ST LANDRY ST",
    "city": "LAFAYETTE",
    "time": "06/18/2019 - 6:04 PM",
    "due_to": "Vehicle Accident",
    "latitude": 30.22067,
    "longitude": -92.02351
  },
  {
    "address": "E PONT DES MOUTON RD & LOUISIANA AV",
    "city": "LAFAYETTE",
    "time": "06/18/2019 - 5:48 PM",
    "due_to": "Vehicle Accident w/ Injuries",
    "latitude": 30.27233,
    "longitude": -91.99249
  },
  {
    "address": "RUE COUPE CIVIQUE & HECTOR CONNOLY RD",
    "city": "CARENCRO",
    "time": "06/18/2019 - 5:44 PM",
    "due_to": "Vehicle Fire",
    "latitude": 30.32206,
    "longitude": -92.02282
  }
]