[
  {
    "address": "105 I10 EASTBOUND MM105 HW",
    "city": "LAFAYETTE",
    "time": "08/12/2020 - 3:54 PM",
    "due_to": "Stalled Vehicle",
    "latitude": 30.26255,
    "longitude": -92.00867
  },
  {
    "address": "118 SYBIL DR",
    "city": "LAFAYETTE",
    "time": "08/12/2020 - 3:40 PM",
    "due_to": "Fire Investigation",
    "latitude": 30.28458,
    "longitude": -91.98906
  },
  {
    "address": "CAMELLIA BL & SETTLERS TRACE BL",
    "city": "LAFAYETTE",
    "time": "08/12/2020 - 3:33 PM",
    "due_to": "Stalled Vehicle",
    "latitude": 30.16963,
    "longitude": -92.039
  },
  {
    "address": "329 MELODY DR",
    "city": "LAFAYETTE",
    "time": "08/12/2020 - 3:24 PM",
    "due_to": "Residential Fire",
    "latitude": 30.16504,
    "longitude": -92.07715
  },
  {
    "address": "W CONGRESS ST & W UNIVERSITY AV",
    "city": "LAFAYETTE",
    "time": "08/12/2020 - 2:56 PM",
    "due_to": "Vehicle Accident",
    "latitude": 30.2261,
    "longitude": -92.02828
  },
  {
    "address": "1003 E ST MARY BL",
    "city": "LAFAYETTE",
    "time": "08/12/2020 - 2:47 PM",
    "due_to": "Vehicle Accident",
    "latitude": 30.20857,
    "longitude": -92.01366
  },
  {
    "address": "1800 NE EVANGELINE TW",
    "city": "LAFAYETTE",
    "time": "08/12/2020 - 11:53 AM",
    "due_to": "Vehicle Accident w/ Injuries",
    "latitude": 30.24592,
    "longitude": -92.01176
  }
]