[
  {
    "address": "720 I10 SOUTH FRONTAGE RD",
    "city": "SCOTT",
    "time": "08/21/2020 - 9:19 PM",
    "due_to": "Vehicle Accident",
    "latitude": 30.24612,
    "longitude": -92.1052
  },
  {
    "address": "128 N GENERAL MARSHALL ST",
    "city": "LAFAYETTE",
    "time": "08/21/2020 - 8:19 PM",
    "due_to": "Residential Fire",
    "latitude": 30.22918,
    "longitude": -91.99753
  },
  {
    "address": "W UNIVERSITY AV & W CONGRESS ST",
    "city": "LAFAYETTE",
    "time": "08/21/2020 - 7:56 PM",
    "due_to": "Vehicle Accident w/ Injuries",
    "latitude": 30.2261,
    "longitude": -92.02828
  },
  {
    "address": "251 NOAH ST",
    "city": "LAFAYETTE",
    "time": "08/21/2020 - 5:35 PM",
    "due_to": "Wire Hazard",
    "latitude": 30.2297978,
    "longitude": -91.9950177
  },
  {
    "address": "1400 BREAUX RD",
    "city": "LAFAYETTE",
    "time": "08/21/2020 - 5:05 PM",
    "due_to": "Grass Fire",
    "latitude": 30.1646001,
    "longitude": -92.1120651
  }
]