[
  {
    "address": "WALLACE BROUSSARD RD & HECTOR CONNOLY RD",
    "city": "CARENCRO",
    "time": "06/02/2019 - 11:49 PM",
    "due_to": "Incoming Call",
    "latitude": 30.32238,
    "longitude": -92.02496
  },
  {
    "address": "N DOMINGUE AV & W CONGRESS ST",
    "city": "LAFAYETTE",
    "time": "06/02/2019 - 11:35 PM",
    "due_to": "Hazardous Material",
    "latitude": 30.19586,
    "longitude": -92.08353
  },
  {
    "address": "111 PEAK VALLEY ST",
    "city": "YOUNGSVILLE",
    "time": "06/02/2019 - 11:24 PM",
    "due_to": "Vehicle Accident",
    "latitude": 30.08844,
    "longitude": -91.97537
  }
]