[
  {
    "address": "4300 JOHNSTON ST",
    "city": "LAFAYETTE",
    "time": "05/13/2020 - 08:25 AM",
    "due_to": "Vehicle Accident",
    "latitude": 30.19526,
    "longitude": -92.05821
  },
  {
    "address": "619 MCKINLEY ST",
    "city": "LAFAYETTE",
    "time": "05/13/2020 - 08:16 AM",
    "due_to": "Fire Alarm-Commercial",
    "latitude": 30.21175,
    "longitude": -92.01625
  },
  {
    "address": "2407 W PINHOOK RD",
    "city": "LAFAYETTE",
    "time": "05/13/2020 - 08:13 AM",
    "due_to": "Vehicle Accident",
    "latitude": 30.18187,
    "longitude": -92.00513
  }
]