[
  {
    "address": "241 DONLON AV",
    "city": "LAFAYETTE",
    "time": "05/25/2020 - 9:49 PM",
    "due_to": "Vehicle Accident",
    "latitude": 30.23983,
    "longitude": -92.01162
  },
  {
    "address": "147 AMBROISE ST",
    "city": "LAFAYETTE",
    "time": "05/25/2020 - 9:46 PM",
    "due_to": "Vehicle Accident",
    "latitude": 30.24128,
    "longitude": -92.01551
  },
  {
    "address": "2390 W CONGRESS ST",
    "city": "LAFAYETTE",
    "time": "05/25/2020 - 7:56 PM",
    "due_to": "Stalled Vehicle",
    "latitude": 30.21551,
    "longitude": -92.04635
  }
]