[
  {
    "address": "JOHNSTON ST & TOUCHET RD",
    "city": "LAFAYETTE",
    "time": "07/31/2020 - 2:43 PM",
    "due_to": "Vehicle Accident",
    "latitude": 30.14443,
    "longitude": -92.09873
  },
  {
    "address": "4000 AMBASSADOR CAFFERY PW",
    "city": "LAFAYETTE",
    "time": "07/31/2020 - 2:38 PM",
    "due_to": "Vehicle Accident w/ Injuries",
    "latitude": 30.1663,
    "longitude": -92.06118
  },
  {
    "address": "1845 W PINHOOK RD",
    "city": "LAFAYETTE",
    "time": "07/31/2020 - 2:32 PM",
    "due_to": "Traffic Control",
    "latitude": 30.18959,
    "longitude": -92.01452
  },
  {
    "address": "AMBASSADOR CAFFERY PW & GUILBEAU RD",
    "city": "LAFAYETTE",
    "time": "07/31/2020 - 2:30 PM",
    "due_to": "Vehicle Accident",
    "latitude": 30.20248,
    "longitude": -92.07527
  },
  {
    "address": "JOHNSTON ST & DOUCET RD",
    "city": "LAFAYETTE",
    "time": "07/31/2020 - 2:21 PM",
    "due_to": "Vehicle Accident",
    "latitude": 30.20341,
    "longitude": -92.04888
  },
  {
    "address": "5130 N UNIVERSITY AV",
    "city": "CARENCRO",
    "time": "07/31/2020 - 2:17 PM",
    "due_to": "Fire Investigation",
    "latitude": 30.32871,
    "longitude": -92.04768
  },
  {
    "address": "SE EVANGELINE TW & E PINHOOK RD",
    "city": "LAFAYETTE",
    "time": "07/31/2020 - 2:12 PM",
    "due_to": "Vehicle Accident w/ Injuries",
    "latitude": 30.21749,
    "longitude": -92.00495
  },
  {
    "address": "JOHNSTON ST & AMBASSADOR CAFFERY PW",
    "city": "LAFAYETTE",
    "time": "07/31/2020 - 1:59 PM",
    "due_to": "Vehicle Accident",
    "latitude": 30.17808,
    "longitude": -92.07452
  },
  {
    "address": "2512 KALISTE SALOOM RD",
    "city": "LAFAYETTE",
    "time": "07/31/2020 - 1:52 PM",
    "due_to": "Vehicle Accident",
    "latitude": 30.15799,
    "longitude": -92.04764
  },
  {
    "address": "W CONGRESS ST & BERTRAND DR",
    "city": "LAFAYETTE",
    "time": "07/31/2020 - 1:46 PM",
    "due_to": "Vehicle Accident",
    "latitude": 30.21493,
    "longitude": -92.04696
  },
  {
    "address": "E PINHOOK RD & SW EVANGELINE TW",
    "city": "LAFAYETTE",
    "time": "07/31/2020 - 1:40 PM",
    "due_to": "Vehicle Accident",
    "latitude": 30.21749,
    "longitude": -92.00495
  }
]