[
  {
    "address": "2700 NE EVANGELINE TW",
    "city": "LAFAYETTE",
    "time": "03/05/2019 - 9:55 PM",
    "due_to": "Vehicle Accident",
    "latitude": 30.2661,
    "longitude": -92.0166
  },
  {
    "address": "W WILLOW ST & ASTER DR",
    "city": "LAFAYETTE",
    "time": "03/05/2019 - 9:46 PM",
    "due_to": "Vehicle Accident",
    "latitude": 30.24441,
    "longitude": -92.04204
  },
  {
    "address": "209 RUFFIAN DR",
    "city": "LAFAYETTE",
    "time": "03/05/2019 - 8:44 PM",
    "due_to": "Vehicle Accident",
    "latitude": 30.30187,
    "longitude": -92.07351
  }
]