[
  {
    "address": "916 LAFAYETTE ST",
    "city": "LAFAYETTE",
    "time": "05/10/2019 - 08:53 AM",
    "due_to": "Fire Investigation",
    "latitude": 30.22351,
    "longitude": -92.0214
  },
  {
    "address": "BERTRAND DR & W CONGRESS ST",
    "city": "LAFAYETTE",
    "time": "05/10/2019 - 08:49 AM",
    "due_to": "Traffic Signal Malfunction",
    "latitude": 30.21493,
    "longitude": -92.04696
  },
  {
    "address": "ALEMEDA ST & NW FRONTAGE RD",
    "city": "LAFAYETTE",
    "time": "05/10/2019 - 08:46 AM",
    "due_to": "Road Hazard",
    "latitude": 30.24279,
    "longitude": -92.01348
  },
  {
    "address": "ARCENEAUX RD & OLA ST",
    "city": "CARENCRO",
    "time": "05/10/2019 - 08:15 AM",
    "due_to": "Vehicle Accident",
    "latitude": 30.30954,
    "longitude": -92.03743
  },
  {
    "address": "400 NW EVANGELINE TW",
    "city": "LAFAYETTE",
    "time": "05/10/2019 - 08:01 AM",
    "due_to": "Stalled Vehicle",
    "latitude": 30.2312,
    "longitude": -92.01377
  },
  {
    "address": "951 GARFIELD ST",
    "city": "LAFAYETTE",
    "time": "05/10/2019 - 07:53 AM",
    "due_to": "Stalled Vehicle",
    "latitude": 30.2189042,
    "longitude": -92.0101686
  },
  {
    "address": "GUILBEAU RD & N DOMINGUE AV",
    "city": "LAFAYETTE",
    "time": "05/10/2019 - 07:08 AM",
    "due_to": "Vehicle Accident",
    "latitude": 30.20263,
    "longitude": -92.08363
  },
  {
    "address": "ST DE PORRES ST & E MAIN ST",
    "city": "BROUSSARD",
    "time": "05/10/2019 - 02:24 AM",
    "due_to": "Wire Hazard",
    "latitude": 30.14521,
    "longitude": -91.95807
  }
]