[
  {
    "address": "120 E GLORIA SWITCH RD",
    "city": "LAFAYETTE",
    "time": "03/17/2019 - 12:55 PM",
    "due_to": "Vehicle Accident",
    "latitude": 30.29346,
    "longitude": -92.02171
  },
  {
    "address": "RENA DR & JOHNSTON DR",
    "city": "LAFAYETTE",
    "time": "03/17/2019 - 12:48 PM",
    "due_to": "Vehicle Accident",
    "latitude": 30.19435,
    "longitude": -92.05813
  },
  {
    "address": "LOUISIANA AV & E WILLOW ST",
    "city": "LAFAYETTE",
    "time": "03/17/2019 - 12:24 PM",
    "due_to": "Vehicle Accident",
    "latitude": 30.24552,
    "longitude": -92.00037
  }
]